README
setup.py
django_payworld/__init__.py
django_payworld/config.py
django_payworld/forms.py
django_payworld/signals.py
django_payworld/urls.py
django_payworld/utils.py
django_payworld/views.py
django_payworld.egg-info/PKG-INFO
django_payworld.egg-info/SOURCES.txt
django_payworld.egg-info/dependency_links.txt
django_payworld.egg-info/requires.txt
django_payworld.egg-info/top_level.txt