Metadata-Version: 1.0
Name: django_payworld
Version: 0.1
Summary: Intergration pay-world.ru for django projects
Home-page: https://bitbucket.com/ib_soft/django_payworld
Author: Ivan A. Anishchuk
Author-email: anishchuk_ia@lavabit.com
License: CC0
Keywords: payment django integration
Platform: UNKNOWN
Classifier: Development Status :: 4 - Beta
Classifier: Environment :: Web Environment
Classifier: Programming Language :: Python :: 2 :: Only
Classifier: Framework :: Django
Classifier: Intended Audience :: Developers
Classifier: License :: CC0 1.0 Universal (CC0 1.0) Public Domain Dedication
